README.md
setup.py
azet/__init__.py
azet.egg-info/PKG-INFO
azet.egg-info/SOURCES.txt
azet.egg-info/dependency_links.txt
azet.egg-info/top_level.txt