Metadata-Version: 2.1
Name: azet
Version: 0
Summary: A local zettelkasten tool
Home-page: UNKNOWN
License: UNKNOWN
Platform: UNKNOWN
